{
  "name": "Penguin Finance",
  "slug": "penguin-finance",
  "tags": [
    "defi"
  ],
  "status": "",
  "highlight": "A protocol bringing yield-farming, staking and more functionalities to the Avalanche platform.",
  "logo": "/img/penguin-finance.png",
  "website": "https://www.penguinfinance.io/",
  "twitter": "https://twitter.com/penguin_defi",
  "telegram": "http://t.me/penguin_defi",
  "github": "",
  "discord": "http://discord.gg/WyFT54acU5",
  "summary": "",
  "docs": "",
  "cmc": "",
  "date": "",
  "token": ""
}